<?xml version="1.0"?>
<col:collection xmlns="http://cnx.rice.edu/collxml" xmlns:col="http://cnx.rice.edu/collxml" xml:lang="en" authors="Liljana Stefanovska">\012  <metadata xmlns:md="http://cnx.rice.edu/mdml" mdml-version="0.5">\012  <md:content-id>col10692</md:content-id>\012  <md:title>&#x424;&#x423;&#x41D;&#x41A;&#x426;&#x418;&#x418; &#x41E;&#x414; &#x41F;&#x41E;&#x412;&#x415;&#x40C;&#x415; &#x41F;&#x420;&#x41E;&#x41C;&#x415;&#x41D;&#x41B;&#x418;&#x412;&#x418;</md:title>\012  \012  \012  <md:license url="http://creativecommons.org/licenses/by/3.0/">Creative Commons Attribution License 3.0</md:license>\012  <md:language>mk</md:language>\012\012  \012\012  \012  \012  \012  \012  \012\012  <md:uuid>e2f750cd-ecfe-4379-896f-196266f57c4a</md:uuid>
<md:slug>funktsii-od-povekje-promenlivi</md:slug>
</metadata>\012\012  <col:content>\012    \012      <col:module document="m21247"/>\012        \012      \012    \012    \012      <col:module document="m21255"/>\012        \012      \012    \012    \012      <col:module document="m21300"/>\012        \012      \012    \012    \012      <col:module document="m21354"/>\012        \012      \012    \012  </col:content>\012</col:collection>
